<?xml version="1.0" encoding="UTF-8"?><theme><formatVersion>7</formatVersion><variables>



<!---------------DUPLICATE AND RENAME THIS FILE BY SYSTEM THEME, EXAMPLE: "megadrive.xml"----------------------->
<!------------------------------------------------AND----------------------------------------------------------->
<!----------------------------ADD YEAR > 1958 BETWEEN <custom.year> AND </custom.year>-------------------------->
<!--------------------------ADD TYPE OF SYSTEM BETWEEN <custom.type> AND </custom.type>------------------------->








<!-- <system.fullName></system.fullName> -->

<custom.year>2003</custom.year><!-- 4 numbers > 1958 -->

<custom.type>system</custom.type><!-- system, port, elements, apps, pinball, collections, images, videos, music -->

<desc>The N-Gage was a mobile gaming device by Nokia that combined a phone and a gaming console, offering a unique gaming experience in the early 2000s.</desc>
<desc lang="fr">Le N-Gage était un dispositif de jeu mobile de Nokia qui combinait un téléphone et une console de jeu, offrant une expérience de jeu unique au début des années 2000.</desc>








<!-------------------------------------------------------------------------------------------------------------->
<!-------------------------------------------------------------------------------------------------------------->
</variables></theme>
