<?xml version="1.0" encoding="UTF-8"?><theme><formatVersion>7</formatVersion><variables>



<!---------------DUPLICATE AND RENAME THIS FILE BY SYSTEM THEME, EXAMPLE: "megadrive.xml"----------------------->
<!------------------------------------------------AND----------------------------------------------------------->
<!----------------------------ADD YEAR > 1958 BETWEEN <custom.year> AND </custom.year>-------------------------->
<!--------------------------ADD TYPE OF SYSTEM BETWEEN <custom.type> AND </custom.type>------------------------->








<!-- <system.fullName></sytem.fullName> -->

<custom.year>1980</custom.year><!-- 4 numbers > 1958 -->

<custom.type>system</custom.type><!-- system, port, elements, apps, pinball, collections, images, videos, music -->

<desc>"The Commodore 20, often referred to as C20, was a home computer by Commodore known for its compact design and early contributions to the personal computing era in the late '70s."</desc>
<desc lang="fr">"Le Commodore 20, souvent désigné sous le nom de C20, était un ordinateur personnel réputé pour son design compact et sa contribution précoce à l'ère de l'informatique personnelle à la fin des années 70."</desc>








<!-------------------------------------------------------------------------------------------------------------->
<!-------------------------------------------------------------------------------------------------------------->
</variables></theme>
