<?xml version="1.0" encoding="UTF-8"?><theme><formatVersion>7</formatVersion><variables>



<!---------------DUPLICATE AND RENAME THIS FILE BY SYSTEM THEME, EXAMPLE: "megadrive.xml"----------------------->
<!------------------------------------------------AND----------------------------------------------------------->
<!----------------------------ADD YEAR > 1958 BETWEEN <custom.year> AND </custom.year>-------------------------->
<!--------------------------ADD TYPE OF SYSTEM BETWEEN <custom.type> AND </custom.type>------------------------->








<!-- <system.fullName></system.fullName> -->

<custom.year>1983</custom.year><!-- 4 numbers > 1958 -->

<custom.type>system</custom.type><!-- system, port, elements, apps, pinball, collections, images, videos, music -->

<desc>Videopac Plus was an upgraded version of the Videopac (Odyssey²) home video game console by Philips, offering enhanced features and a variety of games in the late '70s and early '80s.</desc>
<desc lang="fr">Videopac Plus était une version améliorée de la console de jeu vidéo Videopac (Odyssey²) de Philips, offrant des fonctionnalités améliorées et une variété de jeux à la fin des années 70 et au début des années 80.</desc>








<!-------------------------------------------------------------------------------------------------------------->
<!-------------------------------------------------------------------------------------------------------------->
</variables></theme>
